tests/__init__.py
tests/conftest.py
tests/test_py_octopus.py
web-pyoctopus/__init__.py
web-pyoctopus/api.py
web-pyoctopus/middleware.py
web-pyoctopus/response.py
web_pyoctopus/__init__.py
web_pyoctopus/api.py
web_pyoctopus/middleware.py
web_pyoctopus/response.py
web_pyoctopus-1.0.8.dist-info/METADATA
web_pyoctopus-1.0.8.dist-info/WHEEL
web_pyoctopus-1.0.8.dist-info/top_level.txt
web_pyoctopus-1.0.8.dist-info/RECORD
