Metadata-Version: 2.1
Name: web-pyoctopus
Version: 1.0.8
Summary: Web-PyOctopus is a lightweight Python web framework designed for learning and experimentation, inspired by modern frameworks like Django and FastAPI.
Home-page: UNKNOWN
Author: Muhammad Rajib
Author-email: muhammadrajib199701@gmail.com
License: MIT
Platform: UNKNOWN
Classifier: Programming Language :: Python :: 3.6
Requires-Python: >=3.6.0
Requires-Dist: Jinja2==3.1.6
Requires-Dist: MarkupSafe==2.0.1
Requires-Dist: WebOb==1.8.5
Requires-Dist: parse==1.12.1
Requires-Dist: requests-wsgi-adapter==0.4.1
Requires-Dist: requests==2.22.0
Requires-Dist: whitenoise==4.1.4
